ptmv/__init__.py
ptmv/__main__.py
ptmv/console.py
ptmv/img.py
ptmv/snd.py
ptmv/vid.py
ptmv/yt.py
ptmv-1.0.2.dist-info/LICENSE
ptmv-1.0.2.dist-info/METADATA
ptmv-1.0.2.dist-info/WHEEL
ptmv-1.0.2.dist-info/entry_points.txt
ptmv-1.0.2.dist-info/top_level.txt
ptmv-1.0.2.dist-info/RECORD
