Metadata-Version: 2.1
Name: ptmv
Version: 1.0.2
Summary: An utf-8/truecolor image and video viewer for the terminal
Home-page: https://github.com/kal39/ptmv
Author: kal39
Author-email: kaikitagawajones@gmail.com
License: MIT
Platform: UNKNOWN
Requires-Dist: opencv-python
Requires-Dist: simpleaudio
Requires-Dist: wheel
Requires-Dist: yt-dlp
